{"chunk_definitions":[{"chunk_id":"csetup_chunk","chunk_label":"setup","document_id":"8127CE0E","expansion_state":0,"options":{"engine":"r","include":false,"label":"setup"},"row":9,"row_count":1,"visible":true},{"chunk_id":"ck58wsebd5rvy","chunk_label":"unnamed-chunk-1","document_id":"8127CE0E","expansion_state":0,"options":{"engine":"r","label":"unnamed-chunk-12"},"row":39,"row_count":1,"visible":true},{"chunk_id":"ctwo3n9jze61r","chunk_label":"unnamed-chunk-2","document_id":"8127CE0E","expansion_state":0,"options":{"engine":"r","label":"unnamed-chunk-13"},"row":44,"row_count":1,"visible":true},{"chunk_id":"cfiz7cf3s4g2v","chunk_label":"unnamed-chunk-3","document_id":"8127CE0E","expansion_state":0,"options":{"engine":"r","label":"unnamed-chunk-40"},"row":69,"row_count":1,"visible":true},{"chunk_id":"c7v1hoeshoeka","chunk_label":"unnamed-chunk-3","document_id":"8127CE0E","expansion_state":0,"options":{"engine":"r","label":"unnamed-chunk-14"},"row":70,"row_count":1,"visible":true},{"chunk_id":"cx2na2aascpj1","chunk_label":"unnamed-chunk-4","document_id":"8127CE0E","expansion_state":0,"options":{"engine":"r","label":"unnamed-chunk-15"},"row":74,"row_count":1,"visible":true},{"chunk_id":"c1sdquif9qrpz","chunk_label":"unnamed-chunk-5","document_id":"8127CE0E","expansion_state":0,"options":{"engine":"r","label":"unnamed-chunk-16"},"row":82,"row_count":1,"visible":true},{"chunk_id":"cf8mdlh9u4eol","chunk_label":"unnamed-chunk-10","document_id":"8127CE0E","expansion_state":0,"options":{"engine":"r","label":"unnamed-chunk-25"},"row":109,"row_count":1,"visible":true},{"chunk_id":"c18zv28f27l5q","chunk_label":"unnamed-chunk-10","document_id":"8127CE0E","expansion_state":0,"options":{"engine":"r","label":"unnamed-chunk-17"},"row":110,"row_count":1,"visible":true},{"chunk_id":"cwu4ehkujhhj2","chunk_label":"unnamed-chunk-17","document_id":"8127CE0E","expansion_state":0,"options":{"engine":"r","label":"unnamed-chunk-22"},"row":152,"row_count":1,"visible":true},{"chunk_id":"c91f8amw7k8vb","chunk_label":"unnamed-chunk-18","document_id":"8127CE0E","expansion_state":0,"options":{"engine":"r","label":"unnamed-chunk-44"},"row":156,"row_count":1,"visible":true},{"chunk_id":"c76t4sheqkaqh","chunk_label":"unnamed-chunk-18","document_id":"8127CE0E","expansion_state":0,"options":{"engine":"r","label":"unnamed-chunk-23"},"row":157,"row_count":1,"visible":true},{"chunk_id":"cs7b7l3lbeqmh","chunk_label":"unnamed-chunk-19","document_id":"8127CE0E","expansion_state":0,"options":{"engine":"r","label":"unnamed-chunk-46"},"row":160,"row_count":1,"visible":true},{"chunk_id":"cqpfx9msh56z1","chunk_label":"unnamed-chunk-19","document_id":"8127CE0E","expansion_state":0,"options":{"engine":"r","label":"unnamed-chunk-24"},"row":161,"row_count":1,"visible":true},{"chunk_id":"c57d07zsom228","chunk_label":"unnamed-chunk-20","document_id":"8127CE0E","expansion_state":0,"options":{"engine":"r","label":"unnamed-chunk-47"},"row":170,"row_count":1,"visible":true},{"chunk_id":"cecc3hpexb175","chunk_label":"unnamed-chunk-21","document_id":"8127CE0E","expansion_state":0,"options":{"engine":"r","label":"unnamed-chunk-48"},"row":177,"row_count":1,"visible":true},{"chunk_id":"cu8i7u632b0nf","chunk_label":"unnamed-chunk-22","document_id":"8127CE0E","expansion_state":0,"options":{"engine":"r","label":"unnamed-chunk-19"},"row":191,"row_count":1,"visible":true},{"chunk_id":"csy2cuszuab2h","chunk_label":"unnamed-chunk-23","document_id":"8127CE0E","expansion_state":0,"options":{"engine":"r","label":"unnamed-chunk-36"},"row":199,"row_count":1,"visible":true},{"chunk_id":"cv7313cww6s26","chunk_label":"unnamed-chunk-24","document_id":"8127CE0E","expansion_state":0,"options":{"engine":"r","label":"unnamed-chunk-38"},"row":202,"row_count":1,"visible":true},{"chunk_id":"c7gcjcu7zoarc","chunk_label":"unnamed-chunk-25","document_id":"8127CE0E","expansion_state":0,"options":{"engine":"r","label":"unnamed-chunk-51"},"row":209,"row_count":1,"visible":true},{"chunk_id":"c50yisw4zmsjb","chunk_label":"unnamed-chunk-26","document_id":"8127CE0E","expansion_state":0,"options":{"engine":"r","label":"unnamed-chunk-52"},"row":212,"row_count":1,"visible":true},{"chunk_id":"cc9nc1e3anov3","chunk_label":"unnamed-chunk-28","document_id":"8127CE0E","expansion_state":0,"options":{"engine":"r","label":"unnamed-chunk-54"},"row":230,"row_count":1,"visible":true},{"chunk_id":"cn8kd7y921xxn","chunk_label":"unnamed-chunk-29","document_id":"8127CE0E","expansion_state":0,"options":{"engine":"r","label":"unnamed-chunk-57"},"row":247,"row_count":1,"visible":true},{"chunk_id":"cqmo8wyg75vai","chunk_label":"unnamed-chunk-30","document_id":"8127CE0E","expansion_state":0,"options":{"engine":"r","label":"unnamed-chunk-58"},"row":251,"row_count":1,"visible":true}],"doc_write_time":1587301201}